aio_eth/__init__.py
aio_eth-0.0.1.dist-info/LICENSE
aio_eth-0.0.1.dist-info/METADATA
aio_eth-0.0.1.dist-info/WHEEL
aio_eth-0.0.1.dist-info/top_level.txt
aio_eth-0.0.1.dist-info/RECORD
