Metadata-Version: 2.1
Name: aio-eth
Version: 0.0.1
Summary: A simple python library that can be used to run large Web3 queries on Ethereum blockchain concurrently as per Ethereum JSON-RPC specification.
Home-page: https://github.com/Narasimha1997/pyMigrate
Author: Narasimha Prasanna HN
Author-email: narasimhaprasannahn@gmail.com
License: MIT
Keywords: python web3 ethereum blockchain asyncio aio
Platform: UNKNOWN
Classifier: Programming Language :: Python :: 3
Classifier: License :: OSI Approved :: MIT License
Classifier: Operating System :: OS Independent
Requires-Dist: aiohttp (==3.7.4.post0)
